error_anonymizer.py
error_anonymizer-1.2.4.dist-info/METADATA
error_anonymizer-1.2.4.dist-info/WHEEL
error_anonymizer-1.2.4.dist-info/entry_points.txt
error_anonymizer-1.2.4.dist-info/top_level.txt
error_anonymizer-1.2.4.dist-info/RECORD
