Metadata-Version: 2.1
Name: error-anonymizer
Version: 1.2.4
Summary: Anonymize console error messages by redacting personal info
Home-page: https://github.com/maskedband1t/error-anonymizer
Author: Anurag Akkiraju
Author-email: anurag.akkiraju@gmail.com
License: UNKNOWN
Platform: UNKNOWN
Classifier: Intended Audience :: Developers
Classifier: Programming Language :: Python
Classifier: Programming Language :: Python :: 3
Requires-Dist: setuptools
Requires-Dist: click (==8.1.3)
Requires-Dist: pathlib
